ros_rosidl_runtime_c-4.9.5.data/data/include/rosidl_runtime_c/rosidl_runtime_c/action_type_support_struct.h
ros_rosidl_runtime_c-4.9.5.data/data/include/rosidl_runtime_c/rosidl_runtime_c/message_initialization.h
ros_rosidl_runtime_c-4.9.5.data/data/include/rosidl_runtime_c/rosidl_runtime_c/message_type_support_struct.h
ros_rosidl_runtime_c-4.9.5.data/data/include/rosidl_runtime_c/rosidl_runtime_c/primitives_sequence.h
ros_rosidl_runtime_c-4.9.5.data/data/include/rosidl_runtime_c/rosidl_runtime_c/primitives_sequence_functions.h
ros_rosidl_runtime_c-4.9.5.data/data/include/rosidl_runtime_c/rosidl_runtime_c/sequence_bound.h
ros_rosidl_runtime_c-4.9.5.data/data/include/rosidl_runtime_c/rosidl_runtime_c/service_type_support_struct.h
ros_rosidl_runtime_c-4.9.5.data/data/include/rosidl_runtime_c/rosidl_runtime_c/string.h
ros_rosidl_runtime_c-4.9.5.data/data/include/rosidl_runtime_c/rosidl_runtime_c/string_bound.h
ros_rosidl_runtime_c-4.9.5.data/data/include/rosidl_runtime_c/rosidl_runtime_c/string_functions.h
ros_rosidl_runtime_c-4.9.5.data/data/include/rosidl_runtime_c/rosidl_runtime_c/type_description_utils.h
ros_rosidl_runtime_c-4.9.5.data/data/include/rosidl_runtime_c/rosidl_runtime_c/type_hash.h
ros_rosidl_runtime_c-4.9.5.data/data/include/rosidl_runtime_c/rosidl_runtime_c/u16string.h
ros_rosidl_runtime_c-4.9.5.data/data/include/rosidl_runtime_c/rosidl_runtime_c/u16string_functions.h
ros_rosidl_runtime_c-4.9.5.data/data/include/rosidl_runtime_c/rosidl_runtime_c/visibility_control.h
ros_rosidl_runtime_c-4.9.5.data/data/include/rosidl_runtime_c/rosidl_runtime_c/type_description/field__functions.h
ros_rosidl_runtime_c-4.9.5.data/data/include/rosidl_runtime_c/rosidl_runtime_c/type_description/field__struct.h
ros_rosidl_runtime_c-4.9.5.data/data/include/rosidl_runtime_c/rosidl_runtime_c/type_description/field_type__functions.h
ros_rosidl_runtime_c-4.9.5.data/data/include/rosidl_runtime_c/rosidl_runtime_c/type_description/field_type__struct.h
ros_rosidl_runtime_c-4.9.5.dist-info/METADATA
ros_rosidl_runtime_c-4.9.5.dist-info/WHEEL
ros_rosidl_runtime_c-4.9.5.dist-info/top_level.txt
ros_rosidl_runtime_c-4.9.5.dist-info/RECORD
