Metadata-Version: 2.4
Name: ros-rosidl-runtime-c
Version: 4.9.5
Summary: A ROS package, rosidl_runtime_c provides runtime ROSIDL functionality in C.
Requires-Dist: ros-rosidl-typesupport-interface~=4.9.5
Requires-Dist: ros-rcutils~=6.9.8
Dynamic: description
Dynamic: description-content-type
Dynamic: requires-dist
Dynamic: summary
